metrics_tools/__init__.py
metrics_tools/domain.py
metrics_tools/endpoint_base.py
metrics_tools/errors.py
metrics_tools/keyword.py
metrics_tools/method_base.py
metrics_tools/metrics_tools.py
metrics_tools/response.py
metrics_tools/rest_client.py
metrics_tools/url.py
metrics_tools-0.0.2.dist-info/METADATA
metrics_tools-0.0.2.dist-info/RECORD
metrics_tools-0.0.2.dist-info/WHEEL
metrics_tools-0.0.2.dist-info/top_level.txt
