Metadata-Version: 2.1
Name: metrics-tools
Version: 0.0.2
Summary: Package for making calls to metrics.tools API
Home-page: https://github.com/jonnyblacklabel/metrics_tools
Author: Jonnyblacklabel
Author-email: mail@jonnyblacklabel.de
License: UNKNOWN
Platform: UNKNOWN
Classifier: Programming Language :: Python :: 3.6
Classifier: License :: OSI Approved :: MIT License
Classifier: Operating System :: OS Independent
Requires-Python: >=3.6
Requires-Dist: requests
Requires-Dist: jsonpickle
